easy_import.py
easy_import-0.4.dist-info/LICENSE
easy_import-0.4.dist-info/WHEEL
easy_import-0.4.dist-info/METADATA
easy_import-0.4.dist-info/RECORD
