Metadata-Version: 2.1
Name: easy_import
Version: 0.4
Summary: easy_import.py
Author-email: NerdyTurkey <jwgtisch@gmail.com>
Classifier: License :: OSI Approved :: MIT License
